visactivation/__init__.py
visactivation/function.py
visactivation-0.0.1.dist-info/LICENSE
visactivation-0.0.1.dist-info/METADATA
visactivation-0.0.1.dist-info/WHEEL
visactivation-0.0.1.dist-info/top_level.txt
visactivation-0.0.1.dist-info/RECORD
