Metadata-Version: 2.1
Name: visactivation
Version: 0.0.1
Summary: visualization tool for tensor in CNN
Home-page: https://github.com/YudeWang/visactivation
Author: YudeWang
Author-email: yude.wang@outlook.com
License: UNKNOWN
Platform: UNKNOWN
Classifier: Programming Language :: Python :: 3
Classifier: License :: OSI Approved :: MIT License
Classifier: Operating System :: OS Independent
Requires-Python: >=3.6
Requires-Dist: numpy
Requires-Dist: opencv-python
